PyAudioStream/__init__.py
PyAudioStream/audiostream.py
Tests/__init__.py
Tests/test_audioproperties.py
Tests/test_client.py
Tests/test_message_composing_decomposing.py
Tests/test_server.py
PyAudioStream_TouwaStar-0.0.2.dist-info/LICENSE
PyAudioStream_TouwaStar-0.0.2.dist-info/METADATA
PyAudioStream_TouwaStar-0.0.2.dist-info/WHEEL
PyAudioStream_TouwaStar-0.0.2.dist-info/top_level.txt
PyAudioStream_TouwaStar-0.0.2.dist-info/RECORD
