Metadata-Version: 2.1
Name: PyAudioStream-TouwaStar
Version: 0.0.2
Summary: A library allowing for streaming and playback of audio files from server to client over a socket connection.
Home-page: https://github.com/TouwaStar/PyAudioStream
Author: TouwaStar
Author-email: yowosek@gmail.com
License: UNKNOWN
Platform: UNKNOWN
Classifier: Programming Language :: Python :: 3
Classifier: License :: OSI Approved :: MIT License
Classifier: Operating System :: OS Independent
Requires-Python: >=3.6
